syncloud_lib-354.dist-info/licenses/LICENSE
syncloudlib/__init__.py
syncloudlib/error.py
syncloudlib/fs.py
syncloudlib/http.py
syncloudlib/linux.py
syncloudlib/logger.py
syncloudlib/application/__init__.py
syncloudlib/application/config.py
syncloudlib/application/connection.py
syncloudlib/application/paths.py
syncloudlib/application/ports.py
syncloudlib/application/service.py
syncloudlib/application/storage.py
syncloudlib/application/urls.py
syncloudlib/application/users.py
syncloudlib/integration/__init__.py
syncloudlib/integration/conftest.py
syncloudlib/integration/device.py
syncloudlib/integration/hosts.py
syncloudlib/integration/installer.py
syncloudlib/integration/loop.py
syncloudlib/integration/screenshots.py
syncloudlib/integration/selenium_wrapper.py
syncloudlib/integration/ssh.py
syncloudlib/json/__init__.py
syncloudlib/json/convertible.py
syncloud_lib-354.dist-info/METADATA
syncloud_lib-354.dist-info/WHEEL
syncloud_lib-354.dist-info/top_level.txt
syncloud_lib-354.dist-info/RECORD
