Metadata-Version: 2.4
Name: syncloud-lib
Version: 354
Summary: Syncloud common library
Home-page: https://github.com/syncloud/lib
Author: Syncloud
Author-email: syncloud@syncloud.it
License: GPLv3
License-File: LICENSE
Requires-Dist: retrying==1.4.2
Requires-Dist: jsonpickle==0.7.1
Requires-Dist: requests==2.30.0
Requires-Dist: Jinja2==2.9.6
Requires-Dist: MarkupSafe==2.0.1
Requires-Dist: requests-unixsocket==0.1.5
Dynamic: license-file
